Metadata-Version: 2.1
Name: micropg
Version: 0.3.3
Summary: PostgreSQL database driver for MicroPython
Home-page: https://github.com/nakagami/micropg
Author: Hajime Nakagami
Author-email: nakagami@gmail.com
License: MIT
Keywords: PostgreSQL
License-File: LICENSE
